CHANGES.rst
LICENSE.md
README.md
doc/__init__.py
doc/api.rst
doc/changelog.rst
doc/conf.py
doc/index.rst
doc/requirements.txt
slapd/__init__.py
slapd/certs/README
slapd/certs/ca.conf
slapd/certs/ca.pem
slapd/certs/client.conf
slapd/certs/client.key
slapd/certs/client.pem
slapd/certs/gencerts.sh
slapd/certs/gennssdb.sh
slapd/certs/server.conf
slapd/certs/server.key
slapd/certs/server.pem
tests/__init__.py
tests/test_slapdobject.py
slapd-0.1.6.dist-info/METADATA
slapd-0.1.6.dist-info/WHEEL
slapd-0.1.6.dist-info/licenses/LICENSE.md
slapd-0.1.6.dist-info/RECORD
