Metadata-Version: 2.4
Name: slapd
Version: 0.1.6
Summary: Controls a slapd process in a pythonic way
Project-URL: homepage, https://slapd.readthedocs.io/en/latest
Project-URL: documentation, https://slapd.readthedocs.io/en/latest
Project-URL: repository, https://gitlab.com/python-ldap/python-slapd
Author-email: python-ldap team <python-ldap@python.org>
Maintainer-email: Éloi Rivard <eloi.rivard@aquilenet.fr>
License-Expression: MIT
License-File: LICENSE.md
Keywords: ldap,slapd
Classifier: Intended Audience :: Developers
Classifier: License :: OSI Approved :: MIT License
Classifier: Programming Language :: Python :: 3.8
Classifier: Programming Language :: Python :: 3.9
Classifier: Programming Language :: Python :: 3.10
Classifier: Programming Language :: Python :: 3.11
Classifier: Programming Language :: Python :: 3.12
Classifier: Programming Language :: Python :: Implementation :: CPython
Classifier: Topic :: Software Development :: Libraries :: Python Modules
Requires-Python: >=3.9
